test/__init__.py
test/testclass.py
test/version
rubbergulab_twine_hash_gumbo-0.0.1.dist-info/LICENSE
rubbergulab_twine_hash_gumbo-0.0.1.dist-info/METADATA
rubbergulab_twine_hash_gumbo-0.0.1.dist-info/WHEEL
rubbergulab_twine_hash_gumbo-0.0.1.dist-info/top_level.txt
rubbergulab_twine_hash_gumbo-0.0.1.dist-info/RECORD
